slash_sdk/__init__.py
slash_sdk/_base_client.py
slash_sdk/_client.py
slash_sdk/_compat.py
slash_sdk/_constants.py
slash_sdk/_exceptions.py
slash_sdk/_files.py
slash_sdk/_models.py
slash_sdk/_qs.py
slash_sdk/_resource.py
slash_sdk/_response.py
slash_sdk/_streaming.py
slash_sdk/_types.py
slash_sdk/_version.py
slash_sdk/py.typed
slash_sdk/_utils/__init__.py
slash_sdk/_utils/_logs.py
slash_sdk/_utils/_proxy.py
slash_sdk/_utils/_reflection.py
slash_sdk/_utils/_resources_proxy.py
slash_sdk/_utils/_streams.py
slash_sdk/_utils/_sync.py
slash_sdk/_utils/_transform.py
slash_sdk/_utils/_typing.py
slash_sdk/_utils/_utils.py
slash_sdk/lib/.keep
slash_sdk/resources/__init__.py
slash_sdk/resources/account.py
slash_sdk/resources/card_product.py
slash_sdk/resources/crypto.py
slash_sdk/resources/developer_account.py
slash_sdk/resources/developer_application.py
slash_sdk/resources/legal_entity.py
slash_sdk/resources/merchant.py
slash_sdk/resources/merchant_category.py
slash_sdk/resources/pay.py
slash_sdk/resources/slash_handle.py
slash_sdk/resources/transaction.py
slash_sdk/resources/transfer.py
slash_sdk/resources/virtual_account.py
slash_sdk/resources/webhook.py
slash_sdk/resources/well_known.py
slash_sdk/resources/card/__init__.py
slash_sdk/resources/card/card.py
slash_sdk/resources/card/spending_constraint.py
slash_sdk/resources/card_group/__init__.py
slash_sdk/resources/card_group/card_group.py
slash_sdk/resources/card_group/spending_constraint.py
slash_sdk/resources/fdx/__init__.py
slash_sdk/resources/fdx/customers.py
slash_sdk/resources/fdx/fdx.py
slash_sdk/resources/fdx/accounts/__init__.py
slash_sdk/resources/fdx/accounts/accounts.py
slash_sdk/resources/fdx/accounts/statements.py
slash_sdk/resources/oauth2/__init__.py
slash_sdk/resources/oauth2/oauth2.py
slash_sdk/resources/oauth2/userinfo.py
slash_sdk/types/__init__.py
slash_sdk/types/account.py
slash_sdk/types/account_list_params.py
slash_sdk/types/account_list_response.py
slash_sdk-0.1.0a1.dist-info/METADATA
slash_sdk-0.1.0a1.dist-info/WHEEL
slash_sdk-0.1.0a1.dist-info/licenses/LICENSE
slash_sdk-0.1.0a1.dist-info/RECORD
